buildcat/__init__.py
buildcat/cli.py
buildcat/hou.py
buildcat/modo.py
buildcat/redshift.py
buildcat/worker.py
buildcat-0.5.0.dist-info/entry_points.txt
buildcat-0.5.0.dist-info/LICENSE
buildcat-0.5.0.dist-info/WHEEL
buildcat-0.5.0.dist-info/METADATA
buildcat-0.5.0.dist-info/RECORD
